src/isc_playbook_mcp_server/__init__.py
src/isc_playbook_mcp_server/cleaner.py
src/isc_playbook_mcp_server/hybrid_indexer.py
src/isc_playbook_mcp_server/server.py
isc_playbook_mcp_server/__init__.py
isc_playbook_mcp_server/cleaner.py
isc_playbook_mcp_server/hybrid_indexer.py
isc_playbook_mcp_server/server.py
isc_playbook_mcp_server/data/__init__.py
isc_playbook_mcp_server/data/cleaned/__init__.py
isc_playbook_mcp_server/data/cleaned/cleaned_pages.json
isc_playbook_mcp_server/data/cleaned/index.json
isc_playbook_mcp_server/data/cleaned/stats.json
isc_playbook_mcp_server/data/index/.playbook_hybrid.db.lock
isc_playbook_mcp_server/data/index/__init__.py
isc_playbook_mcp_server/data/index/playbook_hybrid.db
isc_playbook_mcp_server-0.1.2.dist-info/METADATA
isc_playbook_mcp_server-0.1.2.dist-info/WHEEL
isc_playbook_mcp_server-0.1.2.dist-info/entry_points.txt
isc_playbook_mcp_server-0.1.2.dist-info/licenses/LICENSE
isc_playbook_mcp_server-0.1.2.dist-info/RECORD
