Metadata-Version: 2.4
Name: isc-playbook-mcp-server
Version: 0.1.2
Summary: MCP server for searching and browsing the IBM ISC Playbook with hybrid search capabilities
Project-URL: Homepage, https://github.com/yourusername/isc-playbook-mcp-server
Project-URL: Repository, https://github.com/yourusername/isc-playbook-mcp-server
Project-URL: Issues, https://github.com/yourusername/isc-playbook-mcp-server/issues
Author-email: Kirti Nath Jha <kirtijha@in.ibm.com>
License: MIT
License-File: LICENSE
Keywords: hybrid-search,mcp,milvus,playbook,search
Classifier: Development Status :: 4 - Beta
Classifier: Intended Audience :: Developers
Classifier: License :: OSI Approved :: MIT License
Classifier: Programming Language :: Python :: 3
Classifier: Programming Language :: Python :: 3.10
Classifier: Programming Language :: Python :: 3.11
Classifier: Programming Language :: Python :: 3.12
Requires-Python: >=3.10
Requires-Dist: beautifulsoup4>=4.12.0
Requires-Dist: lxml>=4.9.0
Requires-Dist: mcp>=0.9.0
Requires-Dist: milvus-lite>=2.4.0
Requires-Dist: numpy<2.0.0,>=1.24.0
Requires-Dist: pydantic>=2.0.0
Requires-Dist: pymilvus[client]>=2.4.0
Requires-Dist: python-dotenv>=1.0.0
Requires-Dist: sentence-transformers>=2.2.0
Provides-Extra: dev
Requires-Dist: pytest-cov>=4.0.0; extra == 'dev'
Requires-Dist: pytest>=7.0.0; extra == 'dev'
Requires-Dist: ruff>=0.1.0; extra == 'dev'
